mario_gym/Super Mario Bros. (World).nes
mario_gym/__init__.py
Mario_GYM-1.1.dist-info/LICENSE
Mario_GYM-1.1.dist-info/METADATA
Mario_GYM-1.1.dist-info/WHEEL
Mario_GYM-1.1.dist-info/top_level.txt
Mario_GYM-1.1.dist-info/RECORD
