Metadata-Version: 2.1
Name: Mario-GYM
Version: 1.1
Summary: Preprocessed Retro GYM for Super Mario Bros.
Home-page: UNKNOWN
Author: OAO
Author-email: pjh9996@naver.com
License: UNKNOWN
Platform: UNKNOWN
Requires-Python: >=3.6, <3.7
License-File: LICENSE
Requires-Dist: numpy (==1.19.4)
Requires-Dist: gym (==0.17.3)
Requires-Dist: gym-retro (==0.8.0)
Requires-Dist: PyQt6-sip (==13.2.1)
Requires-Dist: PyQt6-Qt6 (==6.2.4)
Requires-Dist: PyQt6 (==6.2.3)
